{
  "generated_at": "2026-04-19T10:22:02.274170+00:00",
  "summary": {
    "total_tickets": 20,
    "resolved_count": 7,
    "escalated_count": 13,
    "resolution_rate": 35.0,
    "escalation_rate": 65.0,
    "category_breakdown": [
      {
        "category": "mobile_login_loop",
        "label": "Mobile login loop",
        "count": 6
      },
      {
        "category": "csv_export",
        "label": "CSV export failures",
        "count": 4
      },
      {
        "category": "duplicate_billing",
        "label": "Duplicate billing",
        "count": 3
      },
      {
        "category": "feature_request",
        "label": "Feature requests",
        "count": 2
      },
      {
        "category": "password_reset",
        "label": "Password reset",
        "count": 1
      },
      {
        "category": "slow_dashboard",
        "label": "Slow dashboard",
        "count": 1
      },
      {
        "category": "invoice_copy",
        "label": "Invoice copy issues",
        "count": 1
      },
      {
        "category": "team_invites",
        "label": "Team invite failures",
        "count": 1
      },
      {
        "category": "search_accuracy",
        "label": "Search accuracy",
        "count": 1
      }
    ],
    "top_recurring_issues": [
      {
        "category": "mobile_login_loop",
        "label": "Mobile login loop",
        "count": 6,
        "resolved": 0,
        "escalated": 6,
        "example_quotes": [
          "On my iPhone in Safari I sign in, finish 2FA, and then land back on the login screen again. I tried three times and c...",
          "After I enter the texted verification code on mobile Safari, the page flashes and sends me back to sign in. Desktop C..."
        ]
      },
      {
        "category": "csv_export",
        "label": "CSV export failures",
        "count": 4,
        "resolved": 0,
        "escalated": 4,
        "example_quotes": [
          "Export to CSV completes but the downloaded file only has headers and no rows. This started today and blocks my financ...",
          "The CSV file downloads, but several columns including customer name are empty even though they appear in the web table."
        ]
      },
      {
        "category": "duplicate_billing",
        "label": "Duplicate billing",
        "count": 3,
        "resolved": 0,
        "escalated": 3,
        "example_quotes": [
          "I upgraded once this morning but my card statement shows two charges from your company. Please confirm whether one wi...",
          "Our admin only clicked upgrade once, but we have two invoice emails and two identical card charges. Please fix this b..."
        ]
      }
    ],
    "escalation_groups": [
      {
        "category": "mobile_login_loop",
        "label": "Mobile login loop",
        "count": 6,
        "reasons": [
          "Persistent login loops on mobile Safari usually need engineering investigation.",
          "Persistent login loops on mobile Safari usually need engineering investigation.",
          "Persistent login loops on mobile Safari usually need engineering investigation."
        ],
        "example_quotes": [
          "On my iPhone in Safari I sign in, finish 2FA, and then land back on the login screen again. I tried three times and c...",
          "After I enter the texted verification code on mobile Safari, the page flashes and sends me back to sign in. Desktop C..."
        ]
      },
      {
        "category": "csv_export",
        "label": "CSV export failures",
        "count": 4,
        "reasons": [
          "CSV export issues are typically product bugs that frontline support cannot patch.",
          "CSV export issues are typically product bugs that frontline support cannot patch.",
          "CSV export issues are typically product bugs that frontline support cannot patch."
        ],
        "example_quotes": [
          "Export to CSV completes but the downloaded file only has headers and no rows. This started today and blocks my financ...",
          "The CSV file downloads, but several columns including customer name are empty even though they appear in the web table."
        ]
      },
      {
        "category": "duplicate_billing",
        "label": "Duplicate billing",
        "count": 3,
        "reasons": [
          "Duplicate billing needs billing-system investigation and refund handling.",
          "Duplicate billing needs billing-system investigation and refund handling.",
          "Duplicate billing needs billing-system investigation and refund handling."
        ],
        "example_quotes": [
          "I upgraded once this morning but my card statement shows two charges from your company. Please confirm whether one wi...",
          "Our admin only clicked upgrade once, but we have two invoice emails and two identical card charges. Please fix this b..."
        ]
      }
    ],
    "sparkline": {
      "days": [
        "12",
        "13",
        "14",
        "15",
        "16",
        "17",
        "18"
      ],
      "counts": [
        3,
        3,
        3,
        3,
        3,
        3,
        2
      ],
      "line": "@@@@@@*"
    }
  },
  "recommendations": [
    {
      "title": "Fix session persistence on mobile Safari to resolve login loops",
      "reason": "Mobile login loops account for 6 tickets (30% of total volume) and 100% were escalated. Users are repeatedly redirected to the login screen after 2FA on iOS/iPad Safari because the session cookie fails to stick. Fixing this will eliminate the highest-volume escalated issue."
    },
    {
      "title": "Resolve CSV export data loss, truncation, and encoding bugs",
      "reason": "CSV export failures generated 4 tickets (20% of total volume) with a 100% escalation rate. Exports are missing columns, truncating at 200 rows, and breaking accented characters. Fixing the export pipeline will unblock critical finance workflows and reduce engineering escalations."
    },
    {
      "title": "Implement idempotency controls in the billing upgrade flow",
      "reason": "Duplicate billing accounts for 3 tickets (15% of total volume) and 100% escalation. Customers are charged twice for a single upgrade click, requiring manual refund intervention. Adding idempotency keys to the upgrade endpoint will prevent double charges and eliminate this high-priority billing issue."
    }
  ],
  "report_markdown": "# Weekly Support Post-Mortem\n\n## This Week at a Glance\n- **Total Ticket Volume:** 20\n- **Resolution Rate:** 35.0% (7 resolved, 13 escalated)\n- **Escalation Rate:** 65.0%\n- **Volume by Day:**\n  `@@@@@@*`\n  Days: 12 13 14 15 16 17 18\n  Counts: 3 3 3 3 3 3 2\n\n## Top 3 Recurring Issues\n1. **Mobile login loop** (6 tickets; 0 resolved, 6 escalated)\n   - \"On my iPhone in Safari I sign in, finish 2FA, and then land back on the login screen again. I tried three times and c...\"\n   - \"After I enter the texted verification code on mobile Safari, the page flashes and sends me back to sign in. Desktop C...\"\n2. **CSV export failures** (4 tickets; 0 resolved, 4 escalated)\n   - \"Export to CSV completes but the downloaded file only has headers and no rows. This started today and blocks my financ...\"\n   - \"The CSV file downloads, but several columns including customer name are empty even though they appear in the web table.\"\n3. **Duplicate billing** (3 tickets; 0 resolved, 3 escalated)\n   - \"I upgraded once this morning but my card statement shows two charges from your company. Please confirm whether one wi...\"\n   - \"Our admin only clicked upgrade once, but we have two invoice emails and two identical card charges. Please fix this b...\"\n\n## What's Getting Escalated and Why\n- **Mobile login loop** (6 escalations)\n  Reason: Persistent login loops on mobile Safari usually need engineering investigation.\n  Example: \"On my iPhone in Safari I sign in, finish 2FA, and then land back on the login screen again. I tried three times and c...\"\n- **CSV export failures** (4 escalations)\n  Reason: CSV export issues are typically product bugs that frontline support cannot patch.\n  Example: \"Export to CSV completes but the downloaded file only has headers and no rows. This started today and blocks my financ...\"\n- **Duplicate billing** (3 escalations)\n  Reason: Duplicate billing needs billing-system investigation and refund handling.\n  Example: \"I upgraded once this morning but my card statement shows two charges from your company. Please confirm whether one wi...\"\n\n## Recommendations for Product Team\n1. **Fix session persistence on mobile Safari to resolve login loops**: Mobile login loops account for 6 tickets (30% of total volume) and 100% were escalated. Users are repeatedly redirected to the login screen after 2FA on iOS/iPad Safari because the session cookie fails to stick. Fixing this will eliminate the highest-volume escalated issue.\n2. **Resolve CSV export data loss, truncation, and encoding bugs**: CSV export failures generated 4 tickets (20% of total volume) with a 100% escalation rate. Exports are missing columns, truncating at 200 rows, and breaking accented characters. Fixing the export pipeline will unblock critical finance workflows and reduce engineering escalations.\n3. **Implement idempotency controls in the billing upgrade flow**: Duplicate billing accounts for 3 tickets (15% of total volume) and 100% escalation. Customers are charged twice for a single upgrade click, requiring manual refund intervention. Adding idempotency keys to the upgrade endpoint will prevent double charges and eliminate this high-priority billing issue."
}